quixand/__init__.py
quixand/config.py
quixand/errors.py
quixand/types.py
quixand/adapters/__init__.py
quixand/adapters/base.py
quixand/adapters/chutes.py
quixand/adapters/local_docker.py
quixand/adapters/remote_http.py
quixand/cli/__init__.py
quixand/cli/main.py
quixand/container/__init__.py
quixand/container/base.py
quixand/container/docker_runtime.py
quixand/container/podman_runtime.py
quixand/core/code.py
quixand/core/files.py
quixand/core/lifecycle.py
quixand/core/playground.py
quixand/core/processes.py
quixand/core/sandbox.py
quixand/core/sandbox_async.py
quixand/core/templates.py
quixand/core/watchdog.py
quixand/utils/__init__.py
quixand/utils/fs.py
quixand/utils/proc.py
quixand/utils/stream.py
quixand-0.1.5.dist-info/METADATA
quixand-0.1.5.dist-info/WHEEL
quixand-0.1.5.dist-info/entry_points.txt
quixand-0.1.5.dist-info/licenses/LICENSE
quixand-0.1.5.dist-info/RECORD
