Metadata-Version: 2.4
Name: quixand
Version: 0.1.5
Summary: Local-first, adapter-pluggable sandboxes for AI code execution (E2B-like API)
Author: Quixand Contributors
License: MIT
License-File: LICENSE
Requires-Python: >=3.10
Requires-Dist: aiofiles>=24.1
Requires-Dist: aiohttp>=3.9
Requires-Dist: anyio>=4.0
Requires-Dist: build>=1.3.0
Requires-Dist: docker>=7.0
Requires-Dist: ipykernel>=6.30.1
Requires-Dist: orjson>=3.10
Requires-Dist: podman>=4.0
Requires-Dist: ptyprocess>=0.7
Requires-Dist: pydantic>=2.6
Requires-Dist: rich>=13.7
Requires-Dist: twine>=6.1.0
Requires-Dist: typer>=0.12
Requires-Dist: websockets>=12.0
Provides-Extra: chutes
Provides-Extra: remote
Requires-Dist: aiohttp>=3.9; extra == 'remote'
